README.md
setup.py
tky/__init__.py
tky/t_dev.py
tky/t_file.py
tky/t_gui.py
tky/t_jde.py
tky/t_msg.py
tky/t_sql.py
tky/t_tsg.py
tky/tky_test.py
tky.egg-info/PKG-INFO
tky.egg-info/SOURCES.txt
tky.egg-info/dependency_links.txt
tky.egg-info/top_level.txt