Metadata-Version: 2.1
Name: tky
Version: 1.1.6
Summary: tang kai yue 个人使用python方法集合
Home-page: https://gitee.com/tangkaiyue/tky
Author: Tang kai yue
Author-email: tky_1314@163.com
Maintainer: Tang kai yue
Maintainer-email: tky_1314@163.com
License: UNKNOWN
Platform: UNKNOWN
Classifier: Programming Language :: Python :: 3
Classifier: License :: OSI Approved :: MIT License
Classifier: Operating System :: OS Independent
Requires-Python: >=3
